[
{"HOUSE-MEDIAN-PRICE": "$1,255,000", "SUBURB-NAME": "Abbotsford"},
{"HOUSE-MEDIAN-PRICE": "$790,000", "SUBURB-NAME": "Croydon"},
{"HOUSE-MEDIAN-PRICE": "$1,435,000", "SUBURB-NAME": "Carlton"},
{"HOUSE-MEDIAN-PRICE": "$611,000", "SUBURB-NAME": "Caroline Springs"},
{"HOUSE-MEDIAN-PRICE": "$2,200,000", "SUBURB-NAME": "Camberwell"},
{"HOUSE-MEDIAN-PRICE": "$1,231,000", "SUBURB-NAME": "Clayton"},
{"HOUSE-MEDIAN-PRICE": "$1,810,000", "SUBURB-NAME": "Caulfield"},
{"HOUSE-MEDIAN-PRICE": "$1,369,000", "SUBURB-NAME": "Clifton Hill"},
{"HOUSE-MEDIAN-PRICE": "$991,000", "SUBURB-NAME": "Coburg"},
{"HOUSE-MEDIAN-PRICE": "$1,155,500", "SUBURB-NAME": "Collingwood"},
{"HOUSE-MEDIAN-PRICE": "$545,000", "SUBURB-NAME": "Craigieburn"},
{"HOUSE-MEDIAN-PRICE": "$1,153,000", "SUBURB-NAME": "Brunswick"},
{"HOUSE-MEDIAN-PRICE": "$1,104,500", "SUBURB-NAME": "Burwood East"},
{"HOUSE-MEDIAN-PRICE": "$751,000", "SUBURB-NAME": "Bundoora"},
{"HOUSE-MEDIAN-PRICE": "$1,494,000", "SUBURB-NAME": "Williamstown"},
{"HOUSE-MEDIAN-PRICE": "$2,392,500", "SUBURB-NAME": "Brighton"},
{"HOUSE-MEDIAN-PRICE": "$495,000", "SUBURB-NAME": "Werribee"},
{"HOUSE-MEDIAN-PRICE": "$1,726,000", "SUBURB-NAME": "Box Hill"},
{"HOUSE-MEDIAN-PRICE": "$1,041,000", "SUBURB-NAME": "Yarraville"},
{"HOUSE-MEDIAN-PRICE": "$540,000", "SUBURB-NAME": "Tarneit"},
{"HOUSE-MEDIAN-PRICE": "$530,000", "SUBURB-NAME": "Sunbury"},
{"HOUSE-MEDIAN-PRICE": "$4,160,000", "SUBURB-NAME": "Toorak"},
{"HOUSE-MEDIAN-PRICE": "$1,326,000", "SUBURB-NAME": "West Melbourne"},
{"HOUSE-MEDIAN-PRICE": "$1,237,500", "SUBURB-NAME": "St Kilda"},
{"HOUSE-MEDIAN-PRICE": "$1,495,000", "SUBURB-NAME": "South Melbourne"},
{"HOUSE-MEDIAN-PRICE": "$900,000", "SUBURB-NAME": "Ringwood"},
{"HOUSE-MEDIAN-PRICE": "$1,171,000", "SUBURB-NAME": "Thornbury"},
{"HOUSE-MEDIAN-PRICE": "$1,267,750", "SUBURB-NAME": "Richmond"},
{"HOUSE-MEDIAN-PRICE": "$820,000", "SUBURB-NAME": "Reservoir"},
{"HOUSE-MEDIAN-PRICE": "$650,000", "SUBURB-NAME": "Point Cook"},
{"HOUSE-MEDIAN-PRICE": "$1,500,000", "SUBURB-NAME": "Prahran"},
{"HOUSE-MEDIAN-PRICE": "$1,000,000", "SUBURB-NAME": "Preston"},
{"HOUSE-MEDIAN-PRICE": "$884,250", "SUBURB-NAME": "Rowville"},
{"HOUSE-MEDIAN-PRICE": "$780,000", "SUBURB-NAME": "Torquay"},
{"HOUSE-MEDIAN-PRICE": "$1,472,500", "SUBURB-NAME": "Port Melbourne"},
{"HOUSE-MEDIAN-PRICE": "$510,000", "SUBURB-NAME": "Pakenham"},
{"HOUSE-MEDIAN-PRICE": "$1,642,500", "SUBURB-NAME": "South Yarra"},
{"HOUSE-MEDIAN-PRICE": "$1,325,000", "SUBURB-NAME": "Northcote"},
{"HOUSE-MEDIAN-PRICE": "$626,500", "SUBURB-NAME": "Narre Warren"},
{"HOUSE-MEDIAN-PRICE": "$1,400,000", "SUBURB-NAME": "Mount Waverley"},
{"HOUSE-MEDIAN-PRICE": "$957,500", "SUBURB-NAME": "Mount Martha"},
{"HOUSE-MEDIAN-PRICE": "$1,190,000", "SUBURB-NAME": "Mount Eliza"},
{"HOUSE-MEDIAN-PRICE": "$800,000", "SUBURB-NAME": "Mornington"},
{"HOUSE-MEDIAN-PRICE": "$900,500", "SUBURB-NAME": "Mulgrave"},
{"HOUSE-MEDIAN-PRICE": "$1,067,000", "SUBURB-NAME": "Mitcham"},
{"HOUSE-MEDIAN-PRICE": "$1,370,000", "SUBURB-NAME": "North Melbourne"},
{"HOUSE-MEDIAN-PRICE": "$1,302,700", "SUBURB-NAME": "Moonee Ponds"},
{"HOUSE-MEDIAN-PRICE": "no data", "SUBURB-NAME": "Melbourne"},
{"HOUSE-MEDIAN-PRICE": "$2,700,000", "SUBURB-NAME": "Malvern"},
{"HOUSE-MEDIAN-PRICE": "$790,000", "SUBURB-NAME": "Keysborough"},
{"HOUSE-MEDIAN-PRICE": "$1,855,000", "SUBURB-NAME": "Kew East"},
{"HOUSE-MEDIAN-PRICE": "no data", "SUBURB-NAME": "Southbank"},
{"HOUSE-MEDIAN-PRICE": "$1,465,000", "SUBURB-NAME": "Ivanhoe"},
{"HOUSE-MEDIAN-PRICE": "$1,030,000", "SUBURB-NAME": "Kensington"},
{"HOUSE-MEDIAN-PRICE": "$2,040,000", "SUBURB-NAME": "Ivanhoe East"},
{"HOUSE-MEDIAN-PRICE": "$545,000", "SUBURB-NAME": "Hoppers Crossing"},
{"HOUSE-MEDIAN-PRICE": "$1,186,500", "SUBURB-NAME": "Heidelberg"},
{"HOUSE-MEDIAN-PRICE": "$1,337,500", "SUBURB-NAME": "Glen Waverley"},
{"HOUSE-MEDIAN-PRICE": "$2,250,000", "SUBURB-NAME": "Hawthorn"},
{"HOUSE-MEDIAN-PRICE": "$731,000", "SUBURB-NAME": "Lilydale"},
{"HOUSE-MEDIAN-PRICE": "$2,000,000", "SUBURB-NAME": "Glen Iris"},
{"HOUSE-MEDIAN-PRICE": "$2,182,500", "SUBURB-NAME": "Kew"},
{"HOUSE-MEDIAN-PRICE": "$840,000", "SUBURB-NAME": "Greensborough"},
{"HOUSE-MEDIAN-PRICE": "$620,000", "SUBURB-NAME": "Frankston"},
{"HOUSE-MEDIAN-PRICE": "$899,500", "SUBURB-NAME": "Footscray"},
{"HOUSE-MEDIAN-PRICE": "$1,021,000", "SUBURB-NAME": "Flemington"},
{"HOUSE-MEDIAN-PRICE": "$1,585,000", "SUBURB-NAME": "Fitzroy"},
{"HOUSE-MEDIAN-PRICE": "$1,350,000", "SUBURB-NAME": "Essendon"},
{"HOUSE-MEDIAN-PRICE": "$608,000", "SUBURB-NAME": "Epping"},
{"HOUSE-MEDIAN-PRICE": "$1,810,000", "SUBURB-NAME": "Elwood"},
{"HOUSE-MEDIAN-PRICE": "$619,000", "SUBURB-NAME": "Dandenong"},
{"HOUSE-MEDIAN-PRICE": "$975,000", "SUBURB-NAME": "Eltham"},
{"HOUSE-MEDIAN-PRICE": "no data", "SUBURB-NAME": "Docklands"},
{"HOUSE-MEDIAN-PRICE": "$1,392,500", "SUBURB-NAME": "Doncaster"},
{"HOUSE-MEDIAN-PRICE": "$3,175,000", "SUBURB-NAME": "East Melbourne"},
{"HOUSE-MEDIAN-PRICE": "$1,950,000", "SUBURB-NAME": "Eaglemont"},
{"HOUSE-MEDIAN-PRICE": "$1,277,500", "SUBURB-NAME": "Box Hill North"},
{"HOUSE-MEDIAN-PRICE": "$755,500", "SUBURB-NAME": "Ferntree Gully"},
{"HOUSE-MEDIAN-PRICE": "$765,000", "SUBURB-NAME": "Boronia"},
{"HOUSE-MEDIAN-PRICE": "$1,400,000", "SUBURB-NAME": "Blackburn"},
{"HOUSE-MEDIAN-PRICE": "$700,000", "SUBURB-NAME": "Berwick"},
{"HOUSE-MEDIAN-PRICE": "$2,305,000", "SUBURB-NAME": "Balwyn"},
{"HOUSE-MEDIAN-PRICE": "$1,488,250", "SUBURB-NAME": "Bentleigh"},
{"HOUSE-MEDIAN-PRICE": "$2,000,000", "SUBURB-NAME": "Armadale"},
{"HOUSE-MEDIAN-PRICE": "$2,170,000", "SUBURB-NAME": "Albert Park"}
]